rewroute/__init__.py
rewroute-0.1.0.dist-info/METADATA
rewroute-0.1.0.dist-info/WHEEL
rewroute-0.1.0.dist-info/top_level.txt
rewroute-0.1.0.dist-info/RECORD
